MANIFEST.in
README.rst
setup.py
Perl_buildtest_config.egg-info/PKG-INFO
Perl_buildtest_config.egg-info/SOURCES.txt
Perl_buildtest_config.egg-info/dependency_links.txt
Perl_buildtest_config.egg-info/requires.txt
Perl_buildtest_config.egg-info/top_level.txt
buildtest/__init__.py
buildtest/perl/code/Algorithm/diff.pl
buildtest/perl/code/AnyData/AnyData.pl
buildtest/perl/code/AppConfig/AppConfig.pl
buildtest/perl/code/AppConfig/Args.pl
buildtest/perl/code/AppConfig/CGI.pl
buildtest/perl/code/AppConfig/File.pl
buildtest/perl/code/AppConfig/GetOpt.pl
buildtest/perl/code/AppConfig/State.pl
buildtest/perl/code/AppConfig/Std.pl
buildtest/perl/code/AppConfig/Sys.pl
buildtest/perl/code/Authen/SASL.pl